<?xml version="1.0" encoding="UTF-8" ?>
<!DOCTYPE mapper
        PUBLIC "-//mybatis.org//DTD Mapper 3.0//EN"
        "http://mybatis.org/dtd/mybatis-3-mapper.dtd">
<mapper namespace="com.example.lecturesystem.modules.user.mapper.UserMapper">

    <resultMap id="UserEntityMap" type="com.example.lecturesystem.modules.user.entity.UserEntity">
        <id property="id" column="id"/>
        <result property="unitId" column="unit_id"/>
        <result property="username" column="username"/>
        <result property="passwordHash" column="password_hash"/>
        <result property="realName" column="real_name"/>
        <result property="jobTitle" column="job_title"/>
        <result property="mobile" column="mobile"/>
        <result property="role" column="role"/>
        <result property="status" column="status"/>
        <result property="parentUserId" column="parent_user_id"/>
        <result property="levelNo" column="level_no"/>
        <result property="treePath" column="tree_path"/>
        <result property="createTime" column="create_time"/>
        <result property="updateTime" column="update_time"/>
        <result property="createUser" column="create_user"/>
        <result property="updateUser" column="update_user"/>
        <result property="isDeleted" column="is_deleted"/>
    </resultMap>

    <select id="findById" resultMap="UserEntityMap">
        SELECT id, unit_id, username, password_hash, real_name, job_title, mobile, role, status,
               parent_user_id, level_no, tree_path,
               create_time, update_time, create_user, update_user, is_deleted
        FROM sys_user
        WHERE id = #{id}
          AND is_deleted = FALSE
    </select>

    <select id="findByUsername" resultMap="UserEntityMap">
        SELECT id, unit_id, username, password_hash, real_name, job_title, mobile, role, status,
               parent_user_id, level_no, tree_path,
               create_time, update_time, create_user, update_user, is_deleted
        FROM sys_user
        WHERE username = #{username}
          AND is_deleted = FALSE
    </select>

    <insert id="insertUser" parameterType="com.example.lecturesystem.modules.user.entity.UserEntity" useGeneratedKeys="true" keyProperty="id">
        INSERT INTO sys_user (
            unit_id, username, password_hash, real_name, job_title, mobile, role, status,
            parent_user_id, level_no, tree_path,
            create_time, update_time, create_user, update_user, is_deleted
        )
        VALUES (
            #{unitId}, #{username}, #{passwordHash}, #{realName}, #{jobTitle}, #{mobile}, #{role}, #{status},
            #{parentUserId}, #{levelNo}, #{treePath},
            #{createTime}, #{updateTime}, #{createUser}, #{updateUser}, #{isDeleted}
        )
    </insert>

    <select id="countPage" resultType="long">
        SELECT COUNT(1)
        FROM sys_user
        WHERE is_deleted = FALSE
        <if test="keywords != null and keywords != ''">
            AND (
                username LIKE CONCAT('%', #{keywords}, '%')
                OR real_name LIKE CONCAT('%', #{keywords}, '%')
                OR mobile LIKE CONCAT('%', #{keywords}, '%')
            )
        </if>
        <if test="status != null">
            AND status = #{status}
        </if>
        <if test="unitId != null">
            AND unit_id = #{unitId}
        </if>
    </select>

    <select id="queryPage" resultType="com.example.lecturesystem.modules.user.vo.UserListItemVO">
        SELECT u.id, u.unit_id, su.unit_name, u.username, u.real_name, u.job_title, u.mobile, u.status,
               parent_user_id, level_no, create_time, update_time
        FROM sys_user u
        LEFT JOIN sys_org_unit su ON su.id = u.unit_id
        WHERE u.is_deleted = FALSE
        <if test="keywords != null and keywords != ''">
            AND (
                u.username LIKE CONCAT('%', #{keywords}, '%')
                OR u.real_name LIKE CONCAT('%', #{keywords}, '%')
                OR u.mobile LIKE CONCAT('%', #{keywords}, '%')
            )
        </if>
        <if test="status != null">
            AND u.status = #{status}
        </if>
        <if test="unitId != null">
            AND u.unit_id = #{unitId}
        </if>
        ORDER BY u.update_time DESC, u.id DESC
        LIMIT #{pageSize} OFFSET #{offset}
    </select>

    <select id="countPageByUserId" resultType="long">
        SELECT COUNT(1)
        FROM sys_user
        WHERE is_deleted = FALSE
          AND id = #{userId}
        <if test="request.keywords != null and request.keywords != ''">
            AND (
                username LIKE CONCAT('%', #{request.keywords}, '%')
                OR real_name LIKE CONCAT('%', #{request.keywords}, '%')
                OR mobile LIKE CONCAT('%', #{request.keywords}, '%')
            )
        </if>
        <if test="request.status != null">
            AND status = #{request.status}
        </if>
    </select>

    <select id="queryPageByUserId" resultType="com.example.lecturesystem.modules.user.vo.UserListItemVO">
        SELECT u.id, u.unit_id, su.unit_name, u.username, u.real_name, u.job_title, u.mobile, u.status,
               parent_user_id, level_no, create_time, update_time
        FROM sys_user u
        LEFT JOIN sys_org_unit su ON su.id = u.unit_id
        WHERE u.is_deleted = FALSE
          AND u.id = #{userId}
        <if test="request.keywords != null and request.keywords != ''">
            AND (
                u.username LIKE CONCAT('%', #{request.keywords}, '%')
                OR u.real_name LIKE CONCAT('%', #{request.keywords}, '%')
                OR u.mobile LIKE CONCAT('%', #{request.keywords}, '%')
            )
        </if>
        <if test="request.status != null">
            AND u.status = #{request.status}
        </if>
        ORDER BY u.update_time DESC, u.id DESC
        LIMIT #{request.pageSize} OFFSET #{request.offset}
    </select>

    <select id="detailById" resultType="com.example.lecturesystem.modules.user.vo.UserDetailVO">
        SELECT u.id, u.unit_id, su.unit_name, u.parent_user_id, u.level_no, u.tree_path,
               u.username, u.real_name, u.job_title, u.mobile, u.status, u.create_time, u.update_time
        FROM sys_user u
        LEFT JOIN sys_org_unit su ON su.id = u.unit_id
        WHERE u.id = #{id}
          AND u.is_deleted = FALSE
    </select>

    <update id="updateUser" parameterType="com.example.lecturesystem.modules.user.entity.UserEntity">
        UPDATE sys_user
        SET unit_id = #{unitId},
            real_name = #{realName},
            job_title = #{jobTitle},
            mobile = #{mobile},
            status = #{status},
            update_time = #{updateTime},
            update_user = #{updateUser}
        WHERE id = #{id}
          AND is_deleted = FALSE
    </update>

    <update id="logicalDelete">
        UPDATE sys_user
        SET is_deleted = TRUE,
            update_time = #{updateTime},
            update_user = #{updateUser}
        WHERE id = #{id}
          AND is_deleted = FALSE
    </update>

    <update id="updatePassword">
        UPDATE sys_user
        SET password_hash = #{passwordHash},
            update_time = #{updateTime},
            update_user = #{updateUser}
        WHERE id = #{id}
          AND is_deleted = FALSE
    </update>
</mapper>
